{"cookies": [{"name": "guest_id", "value": "v1%3A175174145699112794", "domain": ".twitter.com", "path": "/", "expires": 1785955857.8544, "httpOnly": false, "secure": true, "sameSite": "None"}, {"name": "__cf_bm", "value": "AOK6Jt_zCylREt9M6CybtA.ToGPuaPGzTA2PiJ3Qrhg-1751741457-1.0.1.1-Ozc4SSOKovhKRSHplycDgp0kXNC42tjFhoY8iuByXRUXMcP8pCwVUF4WJZhFOEJrbuuhZqX8rIXLKdcw435qjG_5E1EpjeV0XahAM0iROOc", "domain": ".twitter.com", "path": "/", "expires": 1751743257.85509, "httpOnly": true, "secure": true, "sameSite": "None"}, {"name": "guest_id", "value": "v1%3A175174145728789200", "domain": ".x.com", "path": "/", "expires": 1785955858.157778, "httpOnly": false, "secure": true, "sameSite": "None"}, {"name": "__cf_bm", "value": "QA294THr.ZMCFOpZxmgVsAWWbDAKCe_UbcmSr6QJmVE-1751741457-1.0.1.1-OtJzrzGkRcpXaeBMV0kYdAMCsDnBHaDZlvTV0CY2GBkb5_sxsqyOr59xp7x6LlWWc27ZKFSgtL5oo73n.AY0rEN1M9He2PjHFFJS.VZ5IcI", "domain": ".x.com", "path": "/", "expires": 1751743258.158176, "httpOnly": true, "secure": true, "sameSite": "None"}, {"name": "gt", "value": "1941570511844040918", "domain": ".x.com", "path": "/", "expires": 1751750458.30009, "httpOnly": false, "secure": true, "sameSite": "Lax"}, {"name": "kdt", "value": "bpjT6I0SLCx77P9Rqkp1Er2oHGWtfLCVLXx7pZoh", "domain": ".x.com", "path": "/", "expires": 1785956164.118024, "httpOnly": true, "secure": true, "sameSite": "Lax"}, {"name": "auth_token", "value": "28fa4641571340cc68457491453d7352fbb86906", "domain": ".x.com", "path": "/", "expires": 1785956164.118149, "httpOnly": true, "secure": true, "sameSite": "None"}, {"name": "ct0", "value": "febafbc64373b6886c1817bf5d2f2c43f6e1a1eb179ec8a6f6422269e2a9bdc3ad5ac6e11e2fbae93efa1ab40b3ee817dbc35272f878509ef59be25cbb7acfd602ea255d143847bf42db8135b3fbefb8", "domain": ".x.com", "path": "/", "expires": 1785956164.438531, "httpOnly": false, "secure": true, "sameSite": "Lax"}, {"name": "att", "value": "1-aECfrvXLO5Y3R3VDZq8zQbq0tICSi9a3P8g0BxvM", "domain": ".x.com", "path": "/", "expires": 1751828164.782596, "httpOnly": true, "secure": true, "sameSite": "None"}, {"name": "lang", "value": "en", "domain": "x.com", "path": "/", "expires": -1, "httpOnly": false, "secure": false, "sameSite": "Lax"}, {"name": "twid", "value": "u%3D3082898084", "domain": ".x.com", "path": "/", "expires": 1783277766.983747, "httpOnly": false, "secure": true, "sameSite": "None"}], "origins": []}